LICENCE
MANIFEST.in
README.rst
setup.cfg
setup.py
bin/_flamingo-args
bin/_flamingo-build
bin/_flamingo-init
bin/_flamingo-server
bin/_flamingo-shell
bin/flamingo
flamingo/__init__.py
flamingo/pytest.py
flamingo.egg-info/PKG-INFO
flamingo.egg-info/SOURCES.txt
flamingo.egg-info/dependency_links.txt
flamingo.egg-info/entry_points.txt
flamingo.egg-info/requires.txt
flamingo.egg-info/top_level.txt
flamingo/__pycache__/__init__.cpython-310.pyc
flamingo/__pycache__/__init__.cpython-311.pyc
flamingo/__pycache__/__init__.cpython-35.pyc
flamingo/__pycache__/__init__.cpython-37.pyc
flamingo/__pycache__/__init__.cpython-39.pyc
flamingo/__pycache__/default_settings.cpython-35.pyc
flamingo/core/__init__.py
flamingo/core/context.py
flamingo/core/data_model.py
flamingo/core/errors.py
flamingo/core/parser.py
flamingo/core/types.py
flamingo/core/__pycache__/__init__.cpython-310.pyc
flamingo/core/__pycache__/__init__.cpython-311.pyc
flamingo/core/__pycache__/__init__.cpython-35.pyc
flamingo/core/__pycache__/__init__.cpython-37.pyc
flamingo/core/__pycache__/__init__.cpython-39.pyc
flamingo/core/__pycache__/context.cpython-310.pyc
flamingo/core/__pycache__/context.cpython-35.pyc
flamingo/core/__pycache__/context.cpython-37.pyc
flamingo/core/__pycache__/context.cpython-39.pyc
flamingo/core/__pycache__/data_model.cpython-310.pyc
flamingo/core/__pycache__/data_model.cpython-311.pyc
flamingo/core/__pycache__/data_model.cpython-35.pyc
flamingo/core/__pycache__/data_model.cpython-37.pyc
flamingo/core/__pycache__/data_model.cpython-39.pyc
flamingo/core/__pycache__/errors.cpython-310.pyc
flamingo/core/__pycache__/errors.cpython-311.pyc
flamingo/core/__pycache__/errors.cpython-35.pyc
flamingo/core/__pycache__/errors.cpython-37.pyc
flamingo/core/__pycache__/errors.cpython-39.pyc
flamingo/core/__pycache__/parser.cpython-310.pyc
flamingo/core/__pycache__/parser.cpython-35.pyc
flamingo/core/__pycache__/parser.cpython-37.pyc
flamingo/core/__pycache__/parser.cpython-39.pyc
flamingo/core/__pycache__/settings.cpython-35.pyc
flamingo/core/__pycache__/types.cpython-310.pyc
flamingo/core/__pycache__/types.cpython-35.pyc
flamingo/core/__pycache__/types.cpython-37.pyc
