Metadata-Version: 2.1
Name: flamingo
Version: 1.10.1
Summary: Flamingo is a python3-based, pelican-inspired static site generator
Home-page: https://github.com/pengutronix/flamingo
Author: Florian Scherf
Author-email: python@pengutronix.de
License: Apache License 2.0
Classifier: Development Status :: 5 - Production/Stable
Classifier: Environment :: Console
Classifier: Environment :: Web Environment
Classifier: Framework :: AsyncIO
Classifier: Framework :: IPython
Classifier: License :: OSI Approved :: Apache Software License
Classifier: Natural Language :: English
Classifier: Operating System :: Unix
Classifier: Programming Language :: Python :: 3.7
Classifier: Programming Language :: Python :: 3.8
Classifier: Programming Language :: Python :: 3.9
Classifier: Programming Language :: Python :: 3.10
Classifier: Programming Language :: Python :: 3.11
Classifier: Programming Language :: Python :: 3 :: Only
Classifier: Programming Language :: Python :: Implementation
Classifier: Programming Language :: Python :: Implementation :: CPython
Classifier: Topic :: Documentation
Classifier: Topic :: Internet :: WWW/HTTP
Classifier: Topic :: Software Development :: Documentation
Classifier: Topic :: Text Processing
Classifier: Topic :: Text Processing :: Markup :: HTML
Classifier: Topic :: Text Processing :: Markup :: XML
Classifier: Topic :: Utilities
Provides-Extra: chardet
Provides-Extra: coloredlogs
Provides-Extra: feeds
Provides-Extra: full
Provides-Extra: live-server
Provides-Extra: markdown
Provides-Extra: photoswipe
Provides-Extra: pygments
Provides-Extra: sphinx-themes
Provides-Extra: thumbnails
License-File: LICENCE
